[
  {
    "sku": "NZGRMXV87W8HQUH8",
    "service": "AWSLambda",
    "region": "us-west-2",
    "location": "US West (Oregon)",
    "productFamily": "Serverless",
    "instanceType": null,
    "vcpu": null,
    "memory": null,
    "storage": null,
    "os": null,
    "tenancy": null,
    "marketOption": "OnDemand",
    "unit": "Processed-Gigabytes",
    "description": "$0.008 per GiB for of Lambda-Streaming-Response-Processed-Bytes usage in US West (Oregon)",
    "pricePerUnitUSD": 0.008
  },
  {
    "sku": "MP7NQ6MSH3HNCZP6",
    "service": "AWSLambda",
    "region": "us-west-2",
    "location": "US West (Oregon)",
    "productFamily": "Serverless",
    "instanceType": null,
    "vcpu": null,
    "memory": null,
    "storage": null,
    "os": null,
    "tenancy": null,
    "marketOption": "OnDemand",
    "unit": "Lambda-GB-Second",
    "description": "AWS Lambda - Total Compute (Provisioned) - US West (Oregon)",
    "pricePerUnitUSD": 0.0000097222
  },
  {
    "sku": "99SV6YZ2Y5AYSDCP",
    "service": "AWSLambda",
    "region": "us-west-2",
    "location": "US West (Oregon)",
    "productFamily": "Serverless",
    "instanceType": null,
    "vcpu": null,
    "memory": null,
    "storage": null,
    "os": null,
    "tenancy": null,
    "marketOption": "OnDemand",
    "unit": "GB",
    "description": "USD 0.0001397998 per GB for Lambda-SnapStart-Restored-GB usage in US West (Oregon)",
    "pricePerUnitUSD": 0.0001397998
  },
  {
    "sku": "HXET4S4G5F9Y7FP6",
    "service": "AWSLambda",
    "region": "us-west-2",
    "location": "US West (Oregon)",
    "productFamily": "Serverless",
    "instanceType": null,
    "vcpu": null,
    "memory": null,
    "storage": null,
    "os": null,
    "tenancy": null,
    "marketOption": "OnDemand",
    "unit": "GB-Seconds",
    "description": "AWS Lambda - Ephemeral Storage - US West (Oregon)",
    "pricePerUnitUSD": 3.09e-8
  },
  {
    "sku": "ZQVCC2M69R4S79XS",
    "service": "AWSLambda",
    "region": "us-west-2",
    "location": "Any",
    "productFamily": "Serverless",
    "instanceType": null,
    "vcpu": null,
    "memory": null,
    "storage": null,
    "os": null,
    "tenancy": null,
    "marketOption": "OnDemand",
    "unit": "Request",
    "description": "AWS Lambda - Requests Free Tier - 1,000,000 Requests",
    "pricePerUnitUSD": 0
  },
  {
    "sku": "ZCX9CRYDARE655VR",
    "service": "AWSLambda",
    "region": "us-west-2",
    "location": "US West (Oregon)",
    "productFamily": "Serverless",
    "instanceType": null,
    "vcpu": null,
    "memory": null,
    "storage": null,
    "os": null,
    "tenancy": null,
    "marketOption": "OnDemand",
    "unit": "Lambda-GB-Second",
    "description": "AWS Lambda - Provisioned Concurrency for ARM - US West (Oregon)",
    "pricePerUnitUSD": 0.0000033334
  },
  {
    "sku": "T3BEHFG5V4TZDT76",
    "service": "AWSLambda",
    "region": "us-west-2",
    "location": "US West (Oregon)",
    "productFamily": "Serverless",
    "instanceType": null,
    "vcpu": null,
    "memory": null,
    "storage": null,
    "os": null,
    "tenancy": null,
    "marketOption": "OnDemand",
    "unit": "Lambda-GB-Second",
    "description": "AWS Lambda - Total Compute for ARM - US West (Oregon)-Tier-1",
    "pricePerUnitUSD": 0.0000133334
  },
  {
    "sku": "T3BEHFG5V4TZDT76",
    "service": "AWSLambda",
    "region": "us-west-2",
    "location": "US West (Oregon)",
    "productFamily": "Serverless",
    "instanceType": null,
    "vcpu": null,
    "memory": null,
    "storage": null,
    "os": null,
    "tenancy": null,
    "marketOption": "OnDemand",
    "unit": "Lambda-GB-Second",
    "description": "AWS Lambda - Total Compute for ARM - US West (Oregon)-Tier-2",
    "pricePerUnitUSD": 0.0000120001
  },
  {
    "sku": "T3BEHFG5V4TZDT76",
    "service": "AWSLambda",
    "region": "us-west-2",
    "location": "US West (Oregon)",
    "productFamily": "Serverless",
    "instanceType": null,
    "vcpu": null,
    "memory": null,
    "storage": null,
    "os": null,
    "tenancy": null,
    "marketOption": "OnDemand",
    "unit": "Lambda-GB-Second",
    "description": "AWS Lambda - Total Compute for ARM - US West (Oregon)-Tier-3",
    "pricePerUnitUSD": 0.0000106667
  },
  {
    "sku": "XCU6U9G4FCKZQWG9",
    "service": "AWSLambda",
    "region": "us-west-2",
    "location": "US West (Oregon)",
    "productFamily": "Serverless",
    "instanceType": null,
    "vcpu": null,
    "memory": null,
    "storage": null,
    "os": null,
    "tenancy": null,
    "marketOption": "OnDemand",
    "unit": "Second",
    "description": "AWS Lambda - Total Compute - US West (Oregon)-Tier-1",
    "pricePerUnitUSD": 0.0000166667
  },
  {
    "sku": "XCU6U9G4FCKZQWG9",
    "service": "AWSLambda",
    "region": "us-west-2",
    "location": "US West (Oregon)",
    "productFamily": "Serverless",
    "instanceType": null,
    "vcpu": null,
    "memory": null,
    "storage": null,
    "os": null,
    "tenancy": null,
    "marketOption": "OnDemand",
    "unit": "Second",
    "description": "AWS Lambda - Total Compute - US West (Oregon)-Tier-2",
    "pricePerUnitUSD": 0.000015
  },
  {
    "sku": "XCU6U9G4FCKZQWG9",
    "service": "AWSLambda",
    "region": "us-west-2",
    "location": "US West (Oregon)",
    "productFamily": "Serverless",
    "instanceType": null,
    "vcpu": null,
    "memory": null,
    "storage": null,
    "os": null,
    "tenancy": null,
    "marketOption": "OnDemand",
    "unit": "Second",
    "description": "AWS Lambda - Total Compute - US West (Oregon)-Tier-3",
    "pricePerUnitUSD": 0.0000133334
  },
  {
    "sku": "RZ8N2TAQDKPDSHPC",
    "service": "AWSLambda",
    "region": "us-west-2",
    "location": "Any",
    "productFamily": "Serverless",
    "instanceType": null,
    "vcpu": null,
    "memory": null,
    "storage": null,
    "os": null,
    "tenancy": null,
    "marketOption": "OnDemand",
    "unit": "Processed-Gigabytes",
    "description": "Global rate for Lambda-Streaming-Response-Processed-Bytes",
    "pricePerUnitUSD": 0
  },
  {
    "sku": "GMUBWH6SPHXZCXKD",
    "service": "AWSLambda",
    "region": "us-west-2",
    "location": "US West (Oregon)",
    "productFamily": "Serverless",
    "instanceType": null,
    "vcpu": null,
    "memory": null,
    "storage": null,
    "os": null,
    "tenancy": null,
    "marketOption": "OnDemand",
    "unit": "GB-Seconds",
    "description": "USD 0.0000015046 per GB-Second for Lambda-SnapStart-Cached-GB-S usage in US West (Oregon)",
    "pricePerUnitUSD": 0.0000015046
  },
  {
    "sku": "67MDK2GR6PRT8GW8",
    "service": "AWSLambda",
    "region": "us-west-2",
    "location": "US West (Oregon)",
    "productFamily": "Serverless",
    "instanceType": null,
    "vcpu": null,
    "memory": null,
    "storage": null,
    "os": null,
    "tenancy": null,
    "marketOption": "OnDemand",
    "unit": "Lambda-GB-Second",
    "description": "AWS Lambda - Provisioned Concurrency - US West (Oregon)",
    "pricePerUnitUSD": 0.0000041667
  },
  {
    "sku": "ZWHFK83WS2P4WZR6",
    "service": "AWSLambda",
    "region": "us-west-2",
    "location": "US West (Oregon)",
    "productFamily": "Serverless",
    "instanceType": null,
    "vcpu": null,
    "memory": null,
    "storage": null,
    "os": null,
    "tenancy": null,
    "marketOption": "OnDemand",
    "unit": "Request",
    "description": "AWS Lambda - Total Requests - US West (Oregon)",
    "pricePerUnitUSD": 2e-7
  },
  {
    "sku": "UQJDGRGBAJACRYE4",
    "service": "AWSLambda",
    "region": "us-west-2",
    "location": "US West (Oregon)",
    "productFamily": "Serverless",
    "instanceType": null,
    "vcpu": null,
    "memory": null,
    "storage": null,
    "os": null,
    "tenancy": null,
    "marketOption": "OnDemand",
    "unit": "Request",
    "description": "AWS Lambda Edge - Total Requests - US West (Oregon)",
    "pricePerUnitUSD": 6e-7
  },
  {
    "sku": "6SKZPR8753NAAQ4W",
    "service": "AWSLambda",
    "region": "us-west-2",
    "location": "US West (Oregon)",
    "productFamily": "Serverless",
    "instanceType": null,
    "vcpu": null,
    "memory": null,
    "storage": null,
    "os": null,
    "tenancy": null,
    "marketOption": "OnDemand",
    "unit": "Requests",
    "description": "AWS Lambda - Total Requests for ARM - US West (Oregon)",
    "pricePerUnitUSD": 2e-7
  },
  {
    "sku": "NBKU6R2APCBC2G7F",
    "service": "AWSLambda",
    "region": "us-west-2",
    "location": "US West (Oregon)",
    "productFamily": "Serverless",
    "instanceType": null,
    "vcpu": null,
    "memory": null,
    "storage": null,
    "os": null,
    "tenancy": null,
    "marketOption": "OnDemand",
    "unit": "Lambda-GB-Second",
    "description": "AWS Lambda - Total Compute (Provisioned) for ARM - US West (Oregon)",
    "pricePerUnitUSD": 0.0000077778
  },
  {
    "sku": "JRB5VC66Y3RT7ZB6",
    "service": "AWSLambda",
    "region": "us-west-2",
    "location": "US West (Oregon)",
    "productFamily": "Serverless",
    "instanceType": null,
    "vcpu": null,
    "memory": null,
    "storage": null,
    "os": null,
    "tenancy": null,
    "marketOption": "OnDemand",
    "unit": "Event-Poller-Unit-Hours",
    "description": "$0.185 per Event-Poller-Unit-Hour for Lambda-Event-Poller-Unit-Hour in US West (Oregon)",
    "pricePerUnitUSD": 0.185
  },
  {
    "sku": "DU9X9ZR8C8DYH3Y9",
    "service": "AWSLambda",
    "region": "us-west-2",
    "location": "US West (Oregon)",
    "productFamily": "Serverless",
    "instanceType": null,
    "vcpu": null,
    "memory": null,
    "storage": null,
    "os": null,
    "tenancy": null,
    "marketOption": "OnDemand",
    "unit": "Lambda-GB-Second",
    "description": "AWS Lambda Edge - Total Compute - US West (Oregon)",
    "pricePerUnitUSD": 0.00005001
  },
  {
    "sku": "FKVF2FFZFKHXNVJ2",
    "service": "AWSLambda",
    "region": "us-west-2",
    "location": "US West (Oregon)",
    "productFamily": "Serverless",
    "instanceType": null,
    "vcpu": null,
    "memory": null,
    "storage": null,
    "os": null,
    "tenancy": null,
    "marketOption": "OnDemand",
    "unit": "Processed-Gigabytes",
    "description": "$0.008 per GiB for Lambda-Streaming-Response-Processed-Bytes-ARM in US West (Oregon)",
    "pricePerUnitUSD": 0.008
  },
  {
    "sku": "4VCGJ7EG8PJVZG7S",
    "service": "AWSLambda",
    "region": "us-west-2",
    "location": "Any",
    "productFamily": "Serverless",
    "instanceType": null,
    "vcpu": null,
    "memory": null,
    "storage": null,
    "os": null,
    "tenancy": null,
    "marketOption": "OnDemand",
    "unit": "seconds",
    "description": "AWS Lambda - Compute Free Tier - 400,000 GB-Seconds",
    "pricePerUnitUSD": 0
  },
  {
    "sku": "N9TMQ3FMNJR97GYZ",
    "service": "AWSLambda",
    "region": "us-west-2",
    "location": "US West (Oregon)",
    "productFamily": "Serverless",
    "instanceType": null,
    "vcpu": null,
    "memory": null,
    "storage": null,
    "os": null,
    "tenancy": null,
    "marketOption": "OnDemand",
    "unit": "GB-Seconds",
    "description": "AWS Lambda - Ephemeral Storage for ARM - US West (Oregon)",
    "pricePerUnitUSD": 3.09e-8
  }
]